cpu.v
`timescale 1ns/1ps

module memory(
  input wire clk,
  input wire write,
  input wire [31:0] address,
  input wire [31:0] datain,
  output wire [31:0] dataout
);
  reg [31:0] mem [0:63]; // 64 * 4 bytes
  integer i;
  reg [31:0] buffer; //
  // load
  assign dataout = buffer;

  initial begin
    $display("**** RAM ****");
    // initial store into memory
    $readmemh("assout.txt",mem);
    // memmory display
    for (i=0;i<10;i=i+1) $display("M: %0h %h",i , mem[i]);
  end

  always @ (posedge clk) begin
    if (write) mem[address] <= datain;
    buffer <= mem[address];
  end
endmodule

module addressRegister (
  input wire clk,
  // control
  input wire write,
  input wire in1on,
  input wire in2on,
  input wire out1on,
  //input wire out2on,

  input wire [31:0] in1, // in from alu
  input wire [31:0] in2, // in from address incrementer

  output wire [31:0] out1, // out to memory 
  output wire [31:0] out2 // out to address incrementer
);

  reg [31:0] areg;

  // out
  assign out1 = out1on ? areg : 32'bz;
  assign out2 = areg;

  always @ (posedge clk) begin
    // write
    if (in1on & write) areg <= in1;
    else if (in2on & write) areg <= in2;
  end

  initial begin
    areg <= 0;
  end

  endmodule

module addressIncrementer (
  // control
  input wire increment,
  input wire [31:0] datain,
  output wire [31:0] dataout
);
  assign dataout = increment ? datain + 4 : 32'bz;
endmodule

//module instructionDecoder (
  //input clk,
  //// control 
  //input wire getinstr,

  //input wire [31:0] datain,
  //output wire [31:0] instruction
//);
  //reg ireg [31:0];

  //assign instruction = ireg;

  //always @ (posedge clk) begin
    //if (getinstr) ireg <= datain;
  //end
//endmodule

module instructionDecoder (
  input wire clk,

  input wire getinstr, 

  input wire [31:0] datain,
  output wire [31:0] instruction
  //output wire [31:0] controlsignal
);
  reg [31:0] ireg;

  assign instruction = ireg;

  always @ (posedge clk) begin
    if (getinstr) ireg <= datain;
  end
endmodule



// **** CPU ****
module cpu (input clk);

  wire [31:0] memdataout;
  //wire [31:0] memdatain;



  // BUSES
  wire [31:0] alubus;
  wire [31:0] incrementerbus;
  wire [31:0] addressbus;
  wire [31:0] incrinbus;

  // CONTROL SIGNALS
  reg c_addrwrite;
  reg c_addrin1;
  reg c_addrin2;
  reg c_addrout1;
  reg c_addrout2;
  
  reg c_incrementEnable;

  reg c_instrin;

  // MODULES
  memory memoryModule (
    .clk (clk), 
    .write (memwrite), 
    .address (addressbus), 
    .datain (memdatain), 
    .dataout (memdataout)
  );
  addressRegister addressRegisterModule (
    .clk (clk),
    .write (c_addrwrite),
    .in1on (c_addrin1),
    .in2on (c_addrin2),
    .out1on (c_addrout1),
    //.out2on (c_addrout2),
    .in1 (alubus),
    .in2 (incrementerbus),
    .out1 (addressbus),
    .out2 (incrinbus)
  );
  addressIncrementer addressIncrementerModule (
    .increment (c_incrementEnable),
    .datain (incrinbus),
    .dataout (incrementerbus)
  );
  wire [31:0] three;
  instructionDecoder instructionDecoderModule (
    .clk (clk),
    .getinstr (c_instrin),
    .datain (memdataout),
    .instruction (three)
  );











  // FOR TEST
  reg [31:0] cycles = 0;
  always @ (posedge clk) begin
    
    case (cycles)
      // fetch
      0: begin 
        c_addrout1 <= 1; // address register out
      end
      // decode
      1: begin 
        c_addrout1 <= 0;
        // 1
        c_instrin <= 1; // instr decoder in

        c_addrwrite <= 1; // address register point to nextr instr
        c_addrin2 <= 1;
        c_incrementEnable <= 1;
      end
      // execute
      2: begin
        c_instrin <= 0;
        c_addrwrite <= 0;
        c_addrin2 <= 0;
        c_incrementEnable <= 0;
        // 1
      end
    endcase





    #1
    $display("**** CYCLE: %0d ****\n", cycles);
    cycles <= cycles + 1;
  end


endmodule

cpuTB.v
`timescale 1ns/1ps

module cpuTB();
  reg clk = 0;
  always #10 clk <= ~clk; // 50 MHz (1 cycle = 20ns)

  cpu arm7tdmi(.clk (clk));

  initial begin
    $display("**** TESTBENCH ****");
    $dumpfile("cpu.vcd");
    $dumpvars(0);
    #1_000_000 // 1ms
    $finish;
  end
endmodule

// iverilog -o cpu.out cpuTB.v cpu.v && ./cpu.out

cpu.vcd
$date
	Fri Jan  6 06:55:38 2023
$end
$version
	Icarus Verilog
$end
$timescale
	1ps
$end
$scope module cpuTB $end
$var reg 1 ! clk $end
$scope module arm7tdmi $end
$var wire 32 " alubus [31:0] $end
$var wire 1 ! clk $end
$var wire 1 # memwrite $end
$var wire 32 $ three [31:0] $end
$var wire 32 % memdataout [31:0] $end
$var wire 32 & incrinbus [31:0] $end
$var wire 32 ' incrementerbus [31:0] $end
$var wire 32 ( addressbus [31:0] $end
$var reg 1 ) c_addrin1 $end
$var reg 1 * c_addrin2 $end
$var reg 1 + c_addrout1 $end
$var reg 1 , c_addrwrite $end
$var reg 1 - c_incrementEnable $end
$var reg 1 . c_instrin $end
$var reg 32 / cycles [31:0] $end
$scope module addressIncrementerModule $end
$var wire 1 - increment $end
$var wire 32 0 dataout [31:0] $end
$var wire 32 1 datain [31:0] $end
$upscope $end
$scope module addressRegisterModule $end
$var wire 1 ! clk $end
$var wire 32 2 in1 [31:0] $end
$var wire 1 ) in1on $end
$var wire 32 3 in2 [31:0] $end
$var wire 1 * in2on $end
$var wire 1 + out1on $end
$var wire 32 4 out2 [31:0] $end
$var wire 1 , write $end
$var wire 32 5 out1 [31:0] $end
$var reg 32 6 areg [31:0] $end
$upscope $end
$scope module instructionDecoderModule $end
$var wire 1 ! clk $end
$var wire 1 . getinstr $end
$var wire 32 7 instruction [31:0] $end
$var wire 32 8 datain [31:0] $end
$var reg 32 9 ireg [31:0] $end
$upscope $end
$scope module memoryModule $end
$var wire 32 : address [31:0] $end
$var wire 1 ! clk $end
$var wire 32 ; datain [31:0] $end
$var wire 32 < dataout [31:0] $end
$var wire 1 # write $end
$var reg 32 = buffer [31:0] $end
$var integer 32 > i [31:0] $end
$upscope $end
$upscope $end
$upscope $end
$enddefinitions $end
#0
$dumpvars
b1010 >
bx =
bx <
b0z ;
bx :
bx 9
bx 8
bx 7
b0 6
bx 5
b0 4
bx 3
bz 2
b0 1
bx 0
b0 /
x.
x-
x,
x+
x*
x)
bx (
bx '
b0 &
bx %
bx $
z#
bz "
0!
$end
#10000
b0 (
b0 5
b0 :
1+
1!
#11000
b1 /
#20000
0!
#30000
b100 '
b100 0
b100 3
bz (
bz 5
bz :
b11100011101000000111111100000110 %
b11100011101000000111111100000110 8
b11100011101000000111111100000110 <
b11100011101000000111111100000110 =
1-
1*
1,
1.
0+
1!
#31000
b10 /
#40000
0!
#50000
bz '
bz 0
bz 3
bx %
bx 8
bx <
bx =
b100 &
b100 1
b100 4
b100 6
b11100011101000000111111100000110 $
b11100011101000000111111100000110 7
b11100011101000000111111100000110 9
0-
0*
0,
0.
1!
#51000
b11 /
#60000
0!
#70000
1!
#71000
b100 /
#80000
0!
#90000
1!
#91000
b101 /
#100000
0!
#110000
1!
#111000
b110 /
#120000
0!
#130000
1!
#131000
b111 /
#140000
0!
#150000
1!
#151000
b1000 /
#160000
0!
#170000
1!
#171000
b1001 /
#180000
0!
#190000
1!
#191000
b1010 /
#200000
0!
#210000
1!
#211000
b1011 /
#220000
0!
#230000
1!
#231000
b1100 /
#240000
0!
#250000
1!
#251000
b1101 /
#260000
0!
#270000
1!
#271000
b1110 /
#280000
0!
#290000
1!
#291000
b1111 /
#300000
0!
#310000
1!
#311000
b10000 /
#320000
0!
#330000
1!
#331000
b10001 /
#340000
0!
#350000
1!
#351000
b10010 /
#360000
0!
#370000
1!
#371000
b10011 /
#380000
0!
#390000
1!
#391000
b10100 /
#400000
0!
#410000
1!
#411000
b10101 /
#420000
0!
#430000
1!
#431000
b10110 /
#440000
0!
#450000
1!
#451000
b10111 /
#460000
0!
#470000
1!
#471000
b11000 /
#480000
0!
#490000
1!
#491000
b11001 /
