cpuTB.v
`timescale 1ns/1ps

module cpuTB();
  reg clk = 0;
  always #10 clk <= ~clk; // 50 MHz (1 cycle = 20ns)

  cpu arm7tdmi(.clk (clk));

  initial begin
    $display("**** TESTBENCH ****");
    $dumpfile("cpu.vcd");
    $dumpvars(0);
    //#1_000_000 // 1ms
    #200 // 200ns
    $finish;
  end
endmodule

// iverilog -o cpu.out cpuTB.v cpu.v && ./cpu.out

cpu.v
`timescale 1ns/1ps

// special registers
`define PC 15
`define CPSR 16
// flags
`define N 4'b1000
`define Z 4'b0100
`define C 4'b0010
`define V 4'b0001

// **** MODULES **** 
module registerBank(
  input clk,
  input load, // if register is to be written
  input [4:0] select, // selects, which register is to be written (TAKES EFFECT ONLY WHEN regload = 1)
  input [31:0] datain, // data that is to be written
  output [31:0] dataout0, dataout1, dataout2, dataout3, dataout4, dataout5, dataout6, dataout7,
  dataout8, dataout9, dataout10, dataout11, dataout12, dataout13, dataout14, dataout15, dataout16
);
  // 16 base registers + cpsr
  reg [31:0] regs [0:16];
  assign dataout0 = regs[0]; assign dataout1 = regs[1]; assign dataout2 = regs[2]; assign dataout3 = regs[3];
  assign dataout4 = regs[4]; assign dataout5 = regs[5]; assign dataout6 = regs[6]; assign dataout7 = regs[7];
  assign dataout8 = regs[8]; assign dataout9 = regs[9]; assign dataout10 = regs[10]; assign dataout11 = regs[11];
  assign dataout12 = regs[12]; assign dataout13 = regs[13]; assign dataout14 = regs[14]; assign dataout15 = regs[15];
  assign dataout16 = regs[16]; // cpsr

  initial begin
    $display("**** REGISTER BANK ****");
    regs[`CPSR] <= 32'b111010011;
    regs[`PC] <= 0;
  end

  always @(posedge clk) begin
    if (load) regs[select] <= datain;

    // address incrementer (not sure if synthesizable)
    regs[`PC] <= regs[`PC] + 4;
  end 
endmodule

module memory(
  input clk,
  input load, 
  input [31:0] address,
  input [31:0] datain,
  output [31:0] dataout
);
  reg [31:0] mem [0:63]; // 64 * 4 bytes
  integer i;
  // load
  assign dataout = mem[address / 4];

  initial begin
    $display("**** RAM ****");
    // initial store into memory
    $readmemh("assout.txt",mem);
    // memmory display
    for (i=0;i<10;i=i+1) $display("M: %0h %h",i , mem[i]);
  end

  always @(posedge clk) begin
    if (load) mem[address] <= datain;
  end
endmodule





// **** DECODE ****
module instructionDecoder(
  input clk,
  input [31:0] pc, 
  input [31:0] instr
);
  reg [3:0] cond;

  always @(posedge clk) begin
    $display("decoding: %h", instr);
    cond <= instr[31:28];
  end
endmodule

// 11100011101000000111111100000110
// 11100011101000000101111100000111
// 11100011101000000100111100000100
// 11100011101000000010000000000011
// 11100000010001010100001000110111
// 11100000010001010100001000000111





// **** EXECUTE ****
module alu(
  input clk,
  input [31:0] datain1,
  input [31:0] datain2,
  input [3:0] op,
  //output zeroflag,
  output reg [31:0] dataout // todo remove reg
);
  always @(posedge clk) begin
    case (op)
      1: dataout = datain1 & datain2; // AND
      1: dataout = datain1 & datain2; // EOR
      2: dataout = datain1 - datain2; // SUB
      3: dataout = datain2 - datain1; // RSB
      4: dataout = datain1 + datain2; // ADD
      5: dataout = datain1 + datain2; //+ c; // ADC
      6: dataout = datain1 - datain2; //+ c; // SBC
      7: dataout = datain2 - datain1; //+ c; // RSC
      8: dataout = datain1 & datain2; // TST
      9: dataout = datain1 ^ datain2; // TEQ
      10: dataout = datain1 - datain2; // CMP
      11: dataout = datain1 + datain2; // CMN
      12: dataout = datain1 | datain2; // ORR
      13: dataout = datain2; // MOV
      14: dataout = datain1 & ~datain2; // datain2IC
      15: dataout = ~datain2; // MVN
    endcase
  end
endmodule



// **** CPU ****
module cpu(input clk);
  // ** MODULES **
  // register bank
  reg regload;
  reg [4:0] regselect;
  reg [31:0] regdatain;
  wire [31:0] regdataout [0:16];
  registerBank registers(
    .clk (clk),
    .load (regload),
    .select (regselect), 
    .datain (regdatain),
    .dataout0 (regdataout[0]), .dataout1 (regdataout[1]), .dataout2 (regdataout[2]), .dataout3 (regdataout[3]),
    .dataout4 (regdataout[4]), .dataout5 (regdataout[5]), .dataout6 (regdataout[6]), .dataout7 (regdataout[7]),
    .dataout8 (regdataout[8]), .dataout9 (regdataout[9]), .dataout10 (regdataout[10]), .dataout11 (regdataout[11]),
    .dataout12 (regdataout[12]), .dataout13 (regdataout[13]), .dataout14 (regdataout[14]), .dataout15 (regdataout[15]),
    .dataout16 (regdataout[16]));
  // memory
  reg memload;
  wire [31:0] memaddress;
  reg [31:0] memdatain;
  wire [31:0] memdataout;
  memory mem(
    .clk (clk), 
    .load (memload), 
    .address (memaddress), 
    .datain (memdatain), 
    .dataout (memdataout));
  // instruction decoder
  wire [31:0] instruction;
  instructionDecoder decode(
    .clk (clk),
    .pc (regdataout[15]),
    .instr (instruction)
  );

  // ** FETCH **
  assign memaddress = regdataout[`PC];

  // ** DECODE **
  assign instruction = memdataout;
  // ** EXECUTE **
endmodule

cpu.vcd
$date
	Fri Dec 30 15:14:40 2022
$end
$version
	Icarus Verilog
$end
$timescale
	1ps
$end
$scope module alu $end
$var wire 1 ! clk $end
$var wire 32 " datain1 [31:0] $end
$var wire 32 # datain2 [31:0] $end
$var wire 4 $ op [3:0] $end
$var reg 32 % dataout [31:0] $end
$upscope $end
$scope module cpuTB $end
$var reg 1 & clk $end
$scope module arm7tdmi $end
$var wire 1 & clk $end
$var wire 32 ' instruction [31:0] $end
$var wire 32 ( memaddress [31:0] $end
$var wire 32 ) memdataout [31:0] $end
$var reg 32 * memdatain [31:0] $end
$var reg 1 + memload $end
$var reg 32 , regdatain [31:0] $end
$var reg 1 - regload $end
$var reg 5 . regselect [4:0] $end
$scope module decode $end
$var wire 1 & clk $end
$var wire 32 / instr [31:0] $end
$var wire 32 0 pc [31:0] $end
$var reg 4 1 cond [3:0] $end
$upscope $end
$scope module mem $end
$var wire 32 2 address [31:0] $end
$var wire 1 & clk $end
$var wire 32 3 datain [31:0] $end
$var wire 32 4 dataout [31:0] $end
$var wire 1 + load $end
$var integer 32 5 i [31:0] $end
$upscope $end
$scope module registers $end
$var wire 1 & clk $end
$var wire 32 6 datain [31:0] $end
$var wire 32 7 dataout0 [31:0] $end
$var wire 32 8 dataout1 [31:0] $end
$var wire 32 9 dataout10 [31:0] $end
$var wire 32 : dataout11 [31:0] $end
$var wire 32 ; dataout12 [31:0] $end
$var wire 32 < dataout13 [31:0] $end
$var wire 32 = dataout14 [31:0] $end
$var wire 32 > dataout15 [31:0] $end
$var wire 32 ? dataout16 [31:0] $end
$var wire 32 @ dataout2 [31:0] $end
$var wire 32 A dataout3 [31:0] $end
$var wire 32 B dataout4 [31:0] $end
$var wire 32 C dataout5 [31:0] $end
$var wire 32 D dataout6 [31:0] $end
$var wire 32 E dataout7 [31:0] $end
$var wire 32 F dataout8 [31:0] $end
$var wire 32 G dataout9 [31:0] $end
$var wire 1 - load $end
$var wire 5 H select [4:0] $end
$upscope $end
$upscope $end
$upscope $end
$enddefinitions $end
#0
$dumpvars
bx H
bx G
bx F
bx E
bx D
bx C
bx B
bx A
bx @
b111010011 ?
b0 >
bx =
bx <
bx ;
bx :
bx 9
bx 8
bx 7
bx 6
b1010 5
b11100011101000000111111100000110 4
bx 3
b0 2
bx 1
b0 0
b11100011101000000111111100000110 /
bx .
x-
bx ,
x+
bx *
b11100011101000000111111100000110 )
b0 (
b11100011101000000111111100000110 '
0&
bx %
bz $
bz #
bz "
z!
$end
#10000
b11100011101000000101111100000111 '
b11100011101000000101111100000111 /
b11100011101000000101111100000111 )
b11100011101000000101111100000111 4
b100 (
b100 2
b100 0
b100 >
b1110 1
1&
#20000
0&
#30000
b11100011101000000100111100000100 '
b11100011101000000100111100000100 /
b11100011101000000100111100000100 )
b11100011101000000100111100000100 4
b1000 (
b1000 2
b1000 0
b1000 >
1&
#40000
0&
#50000
b11100011101000000010000000000011 '
b11100011101000000010000000000011 /
b11100011101000000010000000000011 )
b11100011101000000010000000000011 4
b1100 (
b1100 2
b1100 0
b1100 >
1&
#60000
0&
#70000
b11100000010001010100001000110111 '
b11100000010001010100001000110111 /
b11100000010001010100001000110111 )
b11100000010001010100001000110111 4
b10000 (
b10000 2
b10000 0
b10000 >
1&
#80000
0&
#90000
b11100000010001010100001000000111 '
b11100000010001010100001000000111 /
b11100000010001010100001000000111 )
b11100000010001010100001000000111 4
b10100 (
b10100 2
b10100 0
b10100 >
1&
#100000
0&
#110000
bx '
bx /
bx )
bx 4
b11000 (
b11000 2
b11000 0
b11000 >
1&
#120000
0&
#130000
b11100 (
b11100 2
b11100 0
b11100 >
bx 1
1&
#140000
0&
#150000
b100000 (
b100000 2
b100000 0
b100000 >
1&
#160000
0&
#170000
b100100 (
b100100 2
b100100 0
b100100 >
1&
#180000
0&
#190000
b101000 (
b101000 2
b101000 0
b101000 >
1&
