cpuTB.v
`timescale 1ns/1ps

module cpuTB();
  reg clk = 0;
  always #10 clk <= ~clk; // 50 MHz (1 cycle = 20ns)

  cpu arm7tdmi(.clk (clk));

  initial begin
    $display("**** TESTBENCH ****");
    $dumpfile("cpu.vcd");
    $dumpvars(0);
    #1_000_000 // 1ms
    $finish;
  end
endmodule

// iverilog -o cpu.out cpuTB.v cpu.v && ./cpu.out

cpu.v
`timescale 1ns/1ps

// special registers
`define PC 15
`define CPSR 16
// flags
`define N 4'b1000
`define Z 4'b0100
`define C 4'b0010
`define V 4'b0001

// **** MODULES **** 
module registerBank(
  input clk,
  input load, // if register is to be written
  input [4:0] select, // selects, which register is to be written (TAKES EFFECT ONLY WHEN regload = 1)
  input [31:0] datain, // data that is to be written
  output [31:0] dataout0, dataout1, dataout2, dataout3, dataout4, dataout5, dataout6, dataout7,
  dataout8, dataout9, dataout10, dataout11, dataout12, dataout13, dataout14, dataout15, dataout16
);
  // 16 base registers + cpsr
  reg [31:0] regs [0:16];
  assign dataout0 = regs[0]; assign dataout1 = regs[1]; assign dataout2 = regs[2]; assign dataout3 = regs[3];
  assign dataout4 = regs[4]; assign dataout5 = regs[5]; assign dataout6 = regs[6]; assign dataout7 = regs[7];
  assign dataout8 = regs[8]; assign dataout9 = regs[9]; assign dataout10 = regs[10]; assign dataout11 = regs[11];
  assign dataout12 = regs[12]; assign dataout13 = regs[13]; assign dataout14 = regs[14]; assign dataout15 = regs[15];
  assign dataout16 = regs[16]; // cpsr

  initial begin
    $display("**** REGISTER BANK ****");
    regs[`CPSR] <= 32'b111010011;
    regs[`PC] <= 0;
  end

  always @(posedge clk) begin
    if (load) regs[select] <= datain;

    // address incrementer (not sure if synthesizable)
    regs[`PC] <= regs[`PC] + 4;
  end 
endmodule

module memory(
  input clk,
  input load, 
  input [31:0] address,
  input [31:0] datain,
  output [31:0] dataout
);
  reg [31:0] mem [0:63]; // 64 * 4 bytes
  integer i;
  // load
  assign dataout = mem[address / 4];

  initial begin
    $display("**** RAM ****");
    // initial store into memory
    $readmemh("assout.txt",mem);
    // memmory display
    for (i=0;i<10;i=i+1) $display("M: %0h %h",i , mem[i]);
  end

  always @(posedge clk) begin
    if (load) mem[address] <= datain;
  end
endmodule





// **** DECODE ****
module instructionDecoder(
  input clk,
  input [31:0] fetchedInstr
);
  reg [31:0] ins; // instruction to decode
  //reg [3:0] cond;

  always @(posedge clk) begin
    ins <= fetchedInstr; 
    $display("decoding: %h", ins);

    if (ins[31:28] != 4'b1111) begin // if condition valid
      //todo case (ins[27:26])
      if (ins[27:26] == 2'b00) begin
          if (ins[25] == 1'b0) begin
            // DATA PROCESSING: reg {shift} (1/2)
            if (!(ins[24:23] == 2'b10 & ins[20] == 1'b0) & ((ins[4] == 1'b0) | (ins[7] == 1'b0 & ins[4] == 1'b1))) begin
              $display("insnum: 0");
            end else if ((ins[24:23] == 2'b10 & ins[20] == 1'b0) & (ins[7] == 1'b0)) begin
              // PSR TRANSFER: mrs reg, msr reg (1/2)
              if (ins[6:4] == 3'b000) begin
                $display("insnum: 1");
              // BRANCH AND EXCHANGE
              end else if (ins[6:4] == 3'b001 & ins[22:21] == 2'b01) begin
                $display("insnum: 5");
              end 
            end else if (ins[24] == 1'b0 & ins[7:4] == 4'b1001) begin
              // MULTIPLY
              if (ins[23:22] == 2'b00) begin
                $display("insnum: 2");
              // MULTIPLY LONG
              end else if (ins[23] == 1'b1) begin
                $display("insnum: 3");
              end
            // HALF WORD DATA TRANSFER
            end else if (!(ins[24] == 1'b0 & ins[21] == 1'b1) | (ins[24] == 1'b0 & ins[21:20] == 2'b10) & (ins[7:4] == 4'b1011 | ins[7:4] == 4'b1101 | ins[7:4] == 4'b1111)) begin
              $display("insnum: 6 or 7");
            // SINGLE DATA SWAP
            end else if (((ins[24:23] == 2'b10 & ins[21:20] == 2'b00) & ins[10:4] == 8'b00001001)) begin
              $display("insnum: 4");
            end
          end else if (ins[25] == 1'b1) begin
            // DATA PROCESSING: imm (2/2)
            if (!(ins[24:23] == 2'b10 & ins[20] == 1'b0)) begin 
              $display("insnum: 0");
            // PSR TRANSFER: msr imm (2/2)
            end else if (ins[24:23] == 2'b10 & ins[21:20] == 2'b10) begin 
              $display("insnum: 1");
            end
          end
      // SINGLE DATA TRANSFER 
      end else if (ins[27:26] == 2'b01) begin
        //todo
        $display("insnum: 8");
      end else if (ins[27:26] == 2'b10) begin
          // BLOCK DATA TRANSFER
          if (ins[25] == 1'b0) begin
            $display("insnum: a");
          // BRANCH
          end else if (ins[25] == 1'b1) begin
            $display("insnum: b");
          end
      end else if (ins[27:26] == 2'b11) begin
        // UNDEFINED
        if (ins[25:21] == 5'b00000) begin
          $display("insnum: 9");
        // SOFTWARE INTERRUPT
        end else if (ins[25:20] == 6'b110000) begin
          $display("insnum: f");
        end 
        // COPROCESSOR...
      end else begin
          // not valid instruction
          $display("invalid instruction");
      end
    end
  end
endmodule


// **** EXECUTE ****
module alu(
  input clk,
  input [31:0] datain1,
  input [31:0] datain2,
  input [3:0] op,
  //output zeroflag,
  output reg [31:0] dataout // todo remove reg
);
  always @(posedge clk) begin
    case (op)
      0: dataout = datain1 & datain2; // AND
      1: dataout = datain1 ^ datain2; // EOR
      2: dataout = datain1 - datain2; // SUB
      3: dataout = datain2 - datain1; // RSB
      4: dataout = datain1 + datain2; // ADD
      5: dataout = datain1 + datain2; //+ c; // ADC
      6: dataout = datain1 - datain2; //+ c; // SBC
      7: dataout = datain2 - datain1; //+ c; // RSC
      8: dataout = datain1 & datain2; // TST
      9: dataout = datain1 ^ datain2; // TEQ
      10: dataout = datain1 - datain2; // CMP
      11: dataout = datain1 + datain2; // CMN
      12: dataout = datain1 | datain2; // ORR
      13: dataout = datain2; // MOV
      14: dataout = datain1 & ~datain2; // datain2IC
      15: dataout = ~datain2; // MVN
    endcase
  end
endmodule

module multiplier(
  input clk,
  input [31:0] datain1,
  input [7:0] datain2,
  output reg [31:0] dataout
);
  always @(posedge clk) begin
    // assign?
    dataout <= datain1 * datain2;
  end
endmodule

module barrelShifter(
  input clk,
  input [31:0] datain,
  output reg [31:0] dataout
);
endmodule


// todo ram shouldnt be within cpu, should it now
// **** CPU ****
module cpu(input clk);
  // ** MODULES **
  // register bank
  reg regload;
  reg [4:0] regselect;
  reg [31:0] regdatain;
  wire [31:0] regdataout [0:16];
  registerBank registers(
    .clk (clk),
    .load (regload),
    .select (regselect), 
    .datain (regdatain),
    .dataout0 (regdataout[0]), .dataout1 (regdataout[1]), .dataout2 (regdataout[2]), .dataout3 (regdataout[3]),
    .dataout4 (regdataout[4]), .dataout5 (regdataout[5]), .dataout6 (regdataout[6]), .dataout7 (regdataout[7]),
    .dataout8 (regdataout[8]), .dataout9 (regdataout[9]), .dataout10 (regdataout[10]), .dataout11 (regdataout[11]),
    .dataout12 (regdataout[12]), .dataout13 (regdataout[13]), .dataout14 (regdataout[14]), .dataout15 (regdataout[15]),
    .dataout16 (regdataout[16]));
  // memory
  reg memload;
  wire [31:0] memaddress;
  reg [31:0] memdatain;
  wire [31:0] memdataout;
  memory mem(
    .clk (clk), 
    .load (memload), 
    .address (memaddress), 
    .datain (memdatain), 
    .dataout (memdataout));
  // instruction decoder
  wire [31:0] instruction;
  instructionDecoder decode(
    .clk (clk),
    .fetchedInstr (instruction)
  );

  // ** FETCH **
  assign memaddress = regdataout[`PC];
  // ** DECODE **
  assign instruction = memdataout;
  // ** EXECUTE **
endmodule

cpu.vcd
$date
	Sat Dec 31 07:27:51 2022
$end
$version
	Icarus Verilog
$end
$timescale
	1ps
$end
$scope module alu $end
$var wire 1 ! clk $end
$var wire 32 " datain1 [31:0] $end
$var wire 32 # datain2 [31:0] $end
$var wire 4 $ op [3:0] $end
$var reg 32 % dataout [31:0] $end
$upscope $end
$scope module barrelShifter $end
$var wire 1 & clk $end
$var wire 32 ' datain [31:0] $end
$var reg 32 ( dataout [31:0] $end
$upscope $end
$scope module cpuTB $end
$var reg 1 ) clk $end
$scope module arm7tdmi $end
$var wire 1 ) clk $end
$var wire 32 * instruction [31:0] $end
$var wire 32 + memaddress [31:0] $end
$var wire 32 , memdataout [31:0] $end
$var reg 32 - memdatain [31:0] $end
$var reg 1 . memload $end
$var reg 32 / regdatain [31:0] $end
$var reg 1 0 regload $end
$var reg 5 1 regselect [4:0] $end
$scope module decode $end
$var wire 1 ) clk $end
$var wire 32 2 fetchedInstr [31:0] $end
$var reg 32 3 ins [31:0] $end
$upscope $end
$scope module mem $end
$var wire 32 4 address [31:0] $end
$var wire 1 ) clk $end
$var wire 32 5 datain [31:0] $end
$var wire 32 6 dataout [31:0] $end
$var wire 1 . load $end
$var integer 32 7 i [31:0] $end
$upscope $end
$scope module registers $end
$var wire 1 ) clk $end
$var wire 32 8 datain [31:0] $end
$var wire 32 9 dataout0 [31:0] $end
$var wire 32 : dataout1 [31:0] $end
$var wire 32 ; dataout10 [31:0] $end
$var wire 32 < dataout11 [31:0] $end
$var wire 32 = dataout12 [31:0] $end
$var wire 32 > dataout13 [31:0] $end
$var wire 32 ? dataout14 [31:0] $end
$var wire 32 @ dataout15 [31:0] $end
$var wire 32 A dataout16 [31:0] $end
$var wire 32 B dataout2 [31:0] $end
$var wire 32 C dataout3 [31:0] $end
$var wire 32 D dataout4 [31:0] $end
$var wire 32 E dataout5 [31:0] $end
$var wire 32 F dataout6 [31:0] $end
$var wire 32 G dataout7 [31:0] $end
$var wire 32 H dataout8 [31:0] $end
$var wire 32 I dataout9 [31:0] $end
$var wire 1 0 load $end
$var wire 5 J select [4:0] $end
$upscope $end
$upscope $end
$upscope $end
$scope module multiplier $end
$var wire 1 K clk $end
$var wire 32 L datain1 [31:0] $end
$var wire 8 M datain2 [7:0] $end
$var reg 32 N dataout [31:0] $end
$upscope $end
$enddefinitions $end
#0
$dumpvars
bx N
bz M
bz L
zK
bx J
bx I
bx H
bx G
bx F
bx E
bx D
bx C
bx B
b111010011 A
b0 @
bx ?
bx >
bx =
bx <
bx ;
bx :
bx 9
bx 8
b1010 7
b11100011101000000111111100000110 6
bx 5
b0 4
bx 3
b11100011101000000111111100000110 2
bx 1
x0
bx /
x.
bx -
b11100011101000000111111100000110 ,
b0 +
b11100011101000000111111100000110 *
0)
bx (
bz '
z&
bx %
bz $
bz #
bz "
z!
$end
#10000
b11100011101000000101111100000111 *
b11100011101000000101111100000111 2
b11100011101000000101111100000111 ,
b11100011101000000101111100000111 6
b100 +
b100 4
b100 @
b11100011101000000111111100000110 3
1)
#20000
0)
#30000
b11100011101000000101111100000111 3
b11100011101000000100111100000100 *
b11100011101000000100111100000100 2
b11100011101000000100111100000100 ,
b11100011101000000100111100000100 6
b1000 +
b1000 4
b1000 @
1)
#40000
0)
#50000
b11100011101000000010000000000011 *
b11100011101000000010000000000011 2
b11100011101000000010000000000011 ,
b11100011101000000010000000000011 6
b1100 +
b1100 4
b1100 @
b11100011101000000100111100000100 3
1)
#60000
0)
#70000
b11100011101000000010000000000011 3
b11100000010001010100001000110111 *
b11100000010001010100001000110111 2
b11100000010001010100001000110111 ,
b11100000010001010100001000110111 6
b10000 +
b10000 4
b10000 @
1)
#80000
0)
#90000
b11100000010001010100001000000111 *
b11100000010001010100001000000111 2
b11100000010001010100001000000111 ,
b11100000010001010100001000000111 6
b10100 +
b10100 4
b10100 @
b11100000010001010100001000110111 3
1)
#100000
0)
#110000
b11100000010001010100001000000111 3
bx *
bx 2
bx ,
bx 6
b11000 +
b11000 4
b11000 @
1)
#120000
0)
#130000
b11100 +
b11100 4
b11100 @
bx 3
1)
#140000
0)
#150000
b100000 +
b100000 4
b100000 @
1)
#160000
0)
#170000
b100100 +
b100100 4
b100100 @
1)
#180000
0)
#190000
b101000 +
b101000 4
b101000 @
1)
