cpu.v
`timescale 1ns/1ps

// ./assembler.py assin.s && iverilog -o cpu.out cpuTB.v cpu.v && ./cpu.out

`define PC 15

// CONTROL SIGNALS (ctrl)
// todo reorder and clean up
// memory
`define c_memwrite 0
// address register
`define c_addrwrite 1
`define c_addrin1 2
`define c_addrin2 3
`define c_addrout1 4
`define c_addrout2 5
// address incrementer 
`define c_incrementenable 6
// register bank
`define c_regwrite 8
`define c_regin1 9
`define c_regin2 10
`define c_regpcwrite 11
`define c_memout 12
`define c_ipipeout 13
`define c_ipipein 14
`define c_dataregin 15
`define c_dataregout 16
`define c_shiftbyimm 17
`define c_shiftvalimm 18


module memory(
  input wire clk,
  input wire write,
  input wire out,
  input wire [31:0] address,
  inout wire [31:0] data
);
  reg [31:0] mem [0:63]; // 64 * 4 bytes
  integer i;
  reg [31:0] buffer; //
  // load
  assign data = out ? buffer : 32'bz;

  initial begin
    // initial store into memory
    $readmemh("assout.txt",mem);
    // memmory display
    for (i=0;i<10;i=i+1) $display("M: %0h %h",i , mem[i]);
  end

  always @ (posedge clk) begin
    //$display(buffer);
    if (write) mem[address / 4] <= data;
    buffer <= mem[address / 4];
  end
endmodule

module addressRegister (
  input wire clk,
  // control
  input wire write,
  input wire in1on,
  input wire in2on,
  input wire out1on,
  //input wire out2on,

  input wire [31:0] in1, // alu bus 
  input wire [31:0] in2, // incrementer bus

  output wire [31:0] out1, // out to memory 
  output wire [31:0] out2 // out to address incrementer
);

  reg [31:0] areg;

  // out
  assign out1 = out1on ? areg : 32'bz;
  assign out2 = areg;

  always @ (posedge clk) begin
    // write
    if (in1on & write) areg <= in1;
    else if (in2on & write) areg <= in2;
  end

  initial begin
    areg <= 0; // todo add to reset
  end
  endmodule

module addressIncrementer (
  // control
  input wire increment,
  input wire [31:0] datain,
  output wire [31:0] dataout
);
  assign dataout = increment ? datain + 4 : 32'bz;
endmodule

//instruction pipeline & read data register (& thumb instruction decoder)
module ipipe (
  input clk,
  input wire inon,
  input wire out1on,
  input wire [31:0] datain,
  output wire [31:0] dataout1, // b bus
  output wire [31:0] dataout2 // instruction decoder
);

  assign dataou1 = out1on ? ireg : 32'bz;
  assign dataout2 = ireg;

  reg [31:0] ireg;
  always @ (posedge clk) begin
    if (inon) ireg <= datain;
  end
endmodule

module writeDataRegister (
  input clk,
  input wire inon,
  input wire outon,
  input wire [31:0] datain,
  output wire [31:0] dataout
);
  reg [31:0] datareg;
  assign dataout = outon ? datareg : 32'bz;
  always @ (posedge clk) begin
    if (inon) datareg <= datain;
  end
endmodule



module instructionDecoder (
  input wire [31:0] ins,
  //output wire [31:0] instruction,
  output reg [31:0] control,

  output reg [31:0] shiftby,
  output reg [1:0] shifttype,
  output reg [3:0] opcode,
  output reg [3:0] rm,
  output reg [3:0] rn,
  output reg [3:0] rd,
  output reg [3:0] rs,
  output reg [31:0] shiftval
);
  always @ (ins) begin
    if (ins[31:28] != 4'b1111) begin // if condition valid
      if (ins[27:26] == 2'b00) begin
          if (ins[25] == 1'b0) begin
            // DATA PROCESSING: reg {shift} (1/2) (i = 0)
            if (!(ins[24:23] == 2'b10 & ins[20] == 1'b0) & ((ins[4] == 1'b0) | (ins[7] == 1'b0 & ins[4] == 1'b1))) begin
              // i, opcode, s, rn, rd, shiftam, shift, t, rm
              $display("\tinsnum: 0 (1/2)");
              // cycleone <= 'h0;
              opcode = ins[24:21];
              rn = ins[19:16];
              rd = ins[15:12];
              rm = ins[3:0];
              shifttype = ins[6:5];
              // todo use c_shiftbyimm for if statement 
              control[`c_shiftvalimm] = 0;
              control[`c_shiftbyimm] = ins[4];
              if (ins[4] == 0)
                shiftby = ins[11:7];
              else
                rs = ins[11:8];
            end else if ((ins[24:23] == 2'b10 & ins[20] == 1'b0) & (ins[7] == 1'b0)) begin
              // PSR TRANSFER: mrs reg, msr reg (1/2)
              if (ins[6:4] == 3'b000) begin
                // i, psr, direction, rd rm
                $display("\tinsnum: 1 (1/2)");
                // cycleone <= 'h1;
              // BRANCH AND EXCHANGE
              end else if (ins[6:4] == 3'b001 & ins[22:21] == 2'b01) begin
                // rn
                $display("\tinsnum: 5");
                // cycleone <= 'h5;
              end 
            end else if (ins[24] == 1'b0 & ins[7:4] == 4'b1001) begin
              // MULTIPLY
              if (ins[23:22] == 2'b00) begin
                // a, s, rd, rn, rs, rm
                $display("\tinsnum: 2");
                // cycleone <= 'h2;
              // MULTIPLY LONG
              end else if (ins[23] == 1'b1) begin
                //u, a, s, rdhi, rdlo, rs, rm
                $display("\tinsnum: 3");
                // cycleone <= 'h3;
              end
            // HALF WORD DATA TRANSFER
            end else if (!(ins[24] == 1'b0 & ins[21] == 1'b1) | (ins[24] == 1'b0 & ins[21:20] == 2'b10) & (ins[7:4] == 4'b1011 | ins[7:4] == 4'b1101 | ins[7:4] == 4'b1111)) begin
              // p, u, i, w, l ,rn, rd, off1, sh, off2,
              $display("\tinsnum: 6 or 7");
              // cycleone <= 'h67; // 6 or 7
            // SINGLE DATA SWAP
            end else if (((ins[24:23] == 2'b10 & ins[21:20] == 2'b00) & ins[10:4] == 8'b00001001)) begin
              // b, rn, rd, rm
              $display("\tinsnum: 4");
              // cycleone <= 'h4;
            end
          end else if (ins[25] == 1'b1) begin
            // DATA PROCESSING: imm (2/2) (i = 1)
            if (!(ins[24:23] == 2'b10 & ins[20] == 1'b0)) begin 
              // i, opcode, s, rn, rd, rotate, imm
              $display("\tinsnum: 0 (2/2)");
              // i, opcode, s, rn, rd, rotate, imm
              // cycleone <= 0;
              opcode = ins[24:21];
              rn = ins[19:16];
              rd = ins[15:12];
              $display(rd);
              shiftby = ins[11:8] * 2; // rotate by
              shifttype = 2'b11;
              shiftval = ins[7:0];
              control[`c_shiftvalimm] = 1;
              control[`c_shiftbyimm] = 1;
            // PSR TRANSFER: msr imm (2/2)
            end else if (ins[24:23] == 2'b10 & ins[21:20] == 2'b10) begin 
              // i, p, u, b, w, l, rn, rd
              $display("\tinsnum: 1 (2/2)");
              // cycleone <= 1;
            end
          end
      // SINGLE DATA TRANSFER 
      end else if (ins[27:26] == 2'b01) begin
        //todo
        // i, p, u, b, w, l, rn, rd, (imm / shiftam, shift, rm)
        $display("\tinsnum: 8");
        // cycleone <= 'h8;
      end else if (ins[27:26] == 2'b10) begin
          // BLOCK DATA TRANSFER
          if (ins[25] == 1'b0) begin
            // p, u, s, w, l, rn, reglist
            $display("\tinsnum: a");
            // cycleone <= 'ha;
          // BRANCH
          end else if (ins[25] == 1'b1) begin
            // l, offset
            $display("\tinsnum: b");
            // cycleone <= 'hb;
          end
      end else if (ins[27:26] == 2'b11) begin
        // UNDEFINED
        if (ins[25:21] == 5'b00000) begin
            $display("\tinsnum: 9");
            // cycleone <= 'h9;
        // SOFTWARE INTERRUPT
        end else if (ins[25:20] == 6'b110000) begin
            $display("\tinsnum: f");
            // cycleone <= 'hf;
        end 
        // COPROCESSOR...
      end else begin
          // not valid instruction
          $display("\tinvalid instruction");
      end
    end
    //$display("\tcontrol signal: %0h", cycleone);
  end
endmodule

module registerBank (
  input wire clk, 
  input wire write,
  input wire in1on,
  input wire in2on,
  input wire pcwrite,
  input wire writeback,

  input wire [31:0] in1, // alu bus
  input wire [31:0] in2, // incrementer bus
  input wire [3:0] rm,
  input wire [3:0] rn,
  input wire [3:0] rs,
  input wire [3:0] rd,
  output wire [31:0] out1, // a bus (rm)
  output wire [31:0] out2, // b bus (rn)
  output wire [31:0] out3 // shiftamountreg (rs)
);
  // 16 base registers + cpsr
  reg [31:0] regs [0:16];

  assign out1 = regs[rm];
  assign out2 = regs[rn];
  assign out3 = regs[rs];

  always @ (posedge clk) begin
    //$display(regs[`PC]);
    // todo
    //if (write) begin
      //if (in1on) regs[rm] <= in1;
      //else if (in2on) regs[rn] <= in2;
    //end

    //if (pcwrite) regs[`PC] <= in2;
    if (writeback) regs[rd] <= in1;
    $display("mov check", regs[2], regs[4], regs[5], regs[7]);
  end
endmodule

module barrelShifter (
  input wire vimm,
  input wire bimm,
  input wire [1:0] type,
  input wire [31:0] valimm, // todo: not sure about the size
  input wire [31:0] valreg, // rm
  input wire [31:0] byimm,
  input wire [31:0] byreg, // rs
  input wire [31:0] datain,
  output reg [31:0] dataout
);
  //assign dataout = datain; // todo: out coerced to in
  parameter width = 32;
  reg [31:0] val;
  reg [31:0] by;

  always @ (*) begin
    if (vimm)
      val = valimm;
    else
      val = valreg;

    if (bimm)
      by = byimm;
    else 
      by = byreg;


    case (type)
      0: begin 
        dataout = 32'b00;
      end
      1: begin 
        dataout =  32'b01;
      end
      2: begin 
        dataout = 32'b10;
      end
      3: begin 
        dataout = (val >> by) | (val << (width - by));
      end
    endcase
  end
endmodule

module alu (
  input wire [3:0] opcode,
  input wire [31:0] dataina,
  input wire [31:0] datainb,
  output reg writeback,
  output reg [31:0] dataout
);
  reg c = 0; // todo (flags)

  always @ (*) begin
    case (opcode)
      0: begin
        dataout = dataina & datainb; // and
        writeback = 1;
      end
      1: begin
        dataout = dataina ^ datainb; // eor 
        writeback = 1;
      end
      2: begin
        dataout = dataina - datainb; // sub
        writeback = 1;
      end
      3: begin 
        dataout = datainb - dataina; // rsb
        writeback = 1;
      end
      4: begin 
        dataout = dataina + datainb; // add 
        writeback = 1;
      end
      5: begin
        dataout = dataina + datainb + c; // adc
        writeback = 1;
      end
      6: begin 
        dataout = dataina - datainb + c; // sbc
        writeback = 1;
      end
      7: begin
        dataout = datainb - dataina + c; // rsc
        writeback = 1;
      end
      8: begin
        dataout = dataina & datainb; // tst
        writeback = 0;
      end
      9: begin
        dataout = dataina ^ datainb; // teq
        writeback = 0;
      end
      10: begin
        dataout = dataina - datainb; // cmp
        writeback = 0;
      end
      11: begin
        dataout = dataina + datainb; // cmn
        writeback = 0;
      end
      12: begin
        dataout = dataina | datainb; // orr
        writeback = 1;
      end
      13: begin
        dataout = datainb; // mov
        writeback = 1;
      end
      14: begin
        dataout = dataina & ~datainb; // bic
        writeback = 1;
      end
      15: begin
        dataout = ~datainb; // mvn
        writeback = 1;
      end
    endcase
  end
endmodule


// **** CPU ****
module cpu (input clk);
  // INPUT SIGNALS (instr)
  // BUSES
  wire [31:0] databus;
  wire [31:0] alubus;
  wire [31:0] incrementerbus;
  wire [31:0] addressbus;
  wire [31:0] abus;
  wire [31:0] bbus;
  wire [31:0] bbusext;
  wire [31:0] incrinbus;
  wire [31:0] decodebus;


  // MODULES
  memory memoryModule (
    .clk (clk), 
    .write (ctrl[`c_memwrite]), 
    //.out (ctrl[`c_memout]),
    .out (1'b1),
    .address (addressbus),
    .data (databus)
  );
  addressRegister addressRegisterModule (
    .clk (clk),
    //.write (ctrl[`c_addrwrite]),
    .write (1'b1),
    .in1on (ctrl[`c_addrin1]),
    //.in2on (ctrl[`c_addrin2]),
    .in2on (1'b1),
    //.out1on (ctrl[`c_addrout1]),
    .out1on (1'b1),
    //.out2on (c_addrout2),
    .in1 (alubus),
    .in2 (incrementerbus),
    .out1 (addressbus),
    .out2 (incrinbus)
  );
  addressIncrementer addressIncrementerModule (
    //.increment (ctrl[`c_incrementenable]),
    .increment (1'b1),
    .datain (incrinbus),
    .dataout (incrementerbus)
  );
  writeDataRegister writeDataRegisterModule (
    .clk (clk),
    .inon (ctrl[`c_dataregin]),
    //.outon (ctrl[`c_dataregout]),
    .outon (1'b0),
    .datain (bbus),
    .dataout (databus)
  );
  ipipe ipipeModule (
    .clk (clk),
    //.inon (ctrl[`c_ipipein]),
    .inon (1'b1),
    //.out1on (ctrl[`c_ipipeout]),
    .out1on (1'b1),
    .datain (databus),
    .dataout1 (bbus),
    .dataout2 (decodebus)
  );
  wire [31:0] ctrl;
  wire [31:0] i_shiftby;
  wire [1:0] i_shifttype;
  wire [3:0] i_opcode;
  wire [3:0] i_rm;
  wire [3:0] i_rn;
  wire [3:0] i_rs;
  wire [3:0] i_rd;
  wire [31:0] i_shiftval;
  instructionDecoder instructionDecoderModule (
    .ins (decodebus),
    //.instruction (instr),
    .control (ctrl),
    .shiftby (i_shiftby),
    .shifttype (i_shifttype),
    .opcode (i_opcode),
    .rm (i_rm),
    .rn (i_rn),
    .rd (i_rd),
    .rs (i_rs),
    .shiftval (i_shiftval)
  );
  wire [31:0] shiftbyreg;
  registerBank registerBankModule (
    .clk (clk),
    .write (ctrl[`c_regwrite]),
    //.in1on (ctrl[`c_regin1]),
    .in1on (1'b1),
    //.in2on (ctrl[`c_regin2]),
    .in2on (1'b1),
    .pcwrite (ctrl[`c_regpcwrite]),
    .writeback (writebackalu),
    .in1 (alubus),
    .in2 (incrementerbus),
    .rm (i_rm),
    .rn (i_rn),
    .rs (i_rs),
    .rd (i_rd),
    .out1 (abus),
    .out2 (bbus),
    .out3 (shiftbyreg)
  );
  barrelShifter barrelShifterModule (
    .vimm (ctrl[`c_shiftvalimm]),
    .bimm (ctrl[`c_shiftbyimm]),
    .type (i_shifttype),
    .valimm (i_shiftval),
    .valreg (bbus),
    .byimm (i_shiftby),
    .byreg (shiftbyreg),
    .datain (bbus),
    .dataout (bbusext)
  );
  wire writebackalu;
  alu aluModule (
    .opcode (i_opcode),
    .dataina (abus),
    .datainb (bbusext),
    .writeback (writebackalu),
    .dataout (alubus)
  );

  // FOR TEST
  reg [31:0] cycles = 0;
  always @ (posedge clk) begin
    
    case (cycles)
      0: begin
        $display("ha");
      end
    endcase

    #1
    $display("**** CYCLE: %0d ****\n", cycles);
    cycles <= cycles + 1;
  end


endmodule

cpuTB.v
`timescale 1ns/1ps

module cpuTB();
  reg clk = 0;
  always #10 clk <= ~clk; // 50 MHz (1 cycle = 20ns)

  cpu arm7tdmi(.clk (clk));

  initial begin
    $display("**** TESTBENCH ****");
    $dumpfile("cpu.vcd");
    $dumpvars(0);
    #1_000_000 // 1ms
    $finish;
  end
endmodule

// iverilog -o cpu.out cpuTB.v cpu.v && ./cpu.out

cpu.vcd
$date
	Sat Jan  7 12:04:40 2023
$end
$version
	Icarus Verilog
$end
$timescale
	1ps
$end
$scope module cpuTB $end
$var reg 1 ! clk $end
$scope module arm7tdmi $end
$var wire 1 ! clk $end
$var wire 32 " databus [31:0] $end
$var wire 1 # writebackalu $end
$var wire 32 $ shiftbyreg [31:0] $end
$var wire 32 % incrinbus [31:0] $end
$var wire 32 & incrementerbus [31:0] $end
$var wire 32 ' i_shiftval [31:0] $end
$var wire 2 ( i_shifttype [1:0] $end
$var wire 32 ) i_shiftby [31:0] $end
$var wire 4 * i_rs [3:0] $end
$var wire 4 + i_rn [3:0] $end
$var wire 4 , i_rm [3:0] $end
$var wire 4 - i_rd [3:0] $end
$var wire 4 . i_opcode [3:0] $end
$var wire 32 / decodebus [31:0] $end
$var wire 32 0 ctrl [31:0] $end
$var wire 32 1 bbusext [31:0] $end
$var wire 32 2 bbus [31:0] $end
$var wire 32 3 alubus [31:0] $end
$var wire 32 4 addressbus [31:0] $end
$var wire 32 5 abus [31:0] $end
$var reg 32 6 cycles [31:0] $end
$scope module addressIncrementerModule $end
$var wire 32 7 dataout [31:0] $end
$var wire 1 8 increment $end
$var wire 32 9 datain [31:0] $end
$upscope $end
$scope module addressRegisterModule $end
$var wire 1 ! clk $end
$var wire 1 : in1on $end
$var wire 32 ; in2 [31:0] $end
$var wire 1 < in2on $end
$var wire 32 = out1 [31:0] $end
$var wire 1 > out1on $end
$var wire 32 ? out2 [31:0] $end
$var wire 1 @ write $end
$var wire 32 A in1 [31:0] $end
$var reg 32 B areg [31:0] $end
$upscope $end
$scope module aluModule $end
$var wire 4 C opcode [3:0] $end
$var wire 32 D datainb [31:0] $end
$var wire 32 E dataina [31:0] $end
$var reg 1 F c $end
$var reg 32 G dataout [31:0] $end
$var reg 1 # writeback $end
$upscope $end
$scope module barrelShifterModule $end
$var wire 1 H bimm $end
$var wire 1 I vimm $end
$var wire 32 J valreg [31:0] $end
$var wire 32 K valimm [31:0] $end
$var wire 2 L type [1:0] $end
$var wire 32 M datain [31:0] $end
$var wire 32 N byreg [31:0] $end
$var wire 32 O byimm [31:0] $end
$var reg 32 P by [31:0] $end
$var reg 32 Q dataout [31:0] $end
$var reg 32 R val [31:0] $end
$upscope $end
$scope module instructionDecoderModule $end
$var wire 32 S ins [31:0] $end
$var reg 32 T control [31:0] $end
$var reg 4 U opcode [3:0] $end
$var reg 4 V rd [3:0] $end
$var reg 4 W rm [3:0] $end
$var reg 4 X rn [3:0] $end
$var reg 4 Y rs [3:0] $end
$var reg 32 Z shiftby [31:0] $end
$var reg 2 [ shifttype [1:0] $end
$var reg 32 \ shiftval [31:0] $end
$upscope $end
$scope module ipipeModule $end
$var wire 1 ! clk $end
$var wire 32 ] datain [31:0] $end
$var wire 32 ^ dataout2 [31:0] $end
$var wire 1 _ inon $end
$var wire 1 ` out1on $end
$var wire 32 a dataout1 [31:0] $end
$var wire 1 b dataou1 $end
$var reg 32 c ireg [31:0] $end
$upscope $end
$scope module memoryModule $end
$var wire 32 d address [31:0] $end
$var wire 1 ! clk $end
$var wire 32 e data [31:0] $end
$var wire 1 f out $end
$var wire 1 g write $end
$var reg 32 h buffer [31:0] $end
$var integer 32 i i [31:0] $end
$upscope $end
$scope module registerBankModule $end
$var wire 1 ! clk $end
$var wire 32 j in1 [31:0] $end
$var wire 1 k in1on $end
$var wire 32 l in2 [31:0] $end
$var wire 1 m in2on $end
$var wire 32 n out1 [31:0] $end
$var wire 32 o out2 [31:0] $end
$var wire 32 p out3 [31:0] $end
$var wire 1 q pcwrite $end
$var wire 4 r rd [3:0] $end
$var wire 4 s rm [3:0] $end
$var wire 4 t rn [3:0] $end
$var wire 4 u rs [3:0] $end
$var wire 1 v write $end
$var wire 1 # writeback $end
$upscope $end
$scope module writeDataRegisterModule $end
$var wire 1 ! clk $end
$var wire 32 w datain [31:0] $end
$var wire 32 x dataout [31:0] $end
$var wire 1 y inon $end
$var wire 1 z outon $end
$var reg 32 { datareg [31:0] $end
$upscope $end
$upscope $end
$upscope $end
$enddefinitions $end
#0
$dumpvars
bx {
0z
xy
bx x
bx w
xv
bx u
bx t
bx s
bx r
xq
bx p
bx o
bx n
1m
b100 l
1k
bx j
b1010 i
bx h
xg
1f
bx e
b0 d
bx c
xb
bx a
1`
1_
bx ^
bx ]
bx \
bx [
bx Z
bx Y
bx X
bx W
bx V
bx U
bx T
bx S
bx R
bx Q
bx P
bx O
bx N
bx M
bx L
bx K
bx J
xI
xH
bx G
0F
bx E
bx D
bx C
b0 B
bx A
1@
b0 ?
1>
b0 =
1<
b100 ;
x:
b0 9
18
b100 7
b0 6
bx 5
b0 4
bx 3
bx 2
bx 1
bx 0
bx /
bx .
bx -
bx ,
bx +
bx *
bx )
bx (
bx '
b100 &
b0 %
bx $
x#
bx "
0!
$end
#10000
b11100011101000000111111100000110 "
b11100011101000000111111100000110 ]
b11100011101000000111111100000110 e
b11100011101000000111111100000110 x
b11100011101000000111111100000110 h
b100 4
b100 =
b100 d
b1000 &
b1000 7
b1000 ;
b1000 l
b100 %
b100 9
b100 ?
b100 B
1!
#11000
b1 6
#20000
0!
#30000
b11000 3
b11000 A
b11000 G
b11000 j
b11000 1
b11000 D
b11000 Q
b11110 P
b110 R
1H
1I
1#
0b
bx11xxxxxxxxxxxxxxxxx 0
bx11xxxxxxxxxxxxxxxxx T
b110 '
b110 K
b110 \
b11 (
b11 L
b11 [
b11110 )
b11110 O
b11110 Z
b111 -
b111 V
b111 r
b0 +
b0 X
b0 t
b1101 .
b1101 C
b1101 U
b11100011101000000111111100000110 /
b11100011101000000111111100000110 S
b11100011101000000111111100000110 ^
b11100011101000000111111100000110 c
b1000 4
b1000 =
b1000 d
b1100 &
b1100 7
b1100 ;
b1100 l
b1000 %
b1000 9
b1000 ?
b1000 B
b11100011101000000101111100000111 "
b11100011101000000101111100000111 ]
b11100011101000000101111100000111 e
b11100011101000000101111100000111 x
b11100011101000000101111100000111 h
1!
#31000
b10 6
#40000
0!
#50000
b11100 3
b11100 A
b11100 G
b11100 j
b11100 1
b11100 D
b11100 Q
b111 R
1b
b111 '
b111 K
b111 \
b101 -
b101 V
b101 r
b11100011101000000100111100000100 "
b11100011101000000100111100000100 ]
b11100011101000000100111100000100 e
b11100011101000000100111100000100 x
b11100011101000000100111100000100 h
b1100 4
b1100 =
b1100 d
b10000 &
b10000 7
b10000 ;
b10000 l
b1100 %
b1100 9
b1100 ?
b1100 B
b11100011101000000101111100000111 /
b11100011101000000101111100000111 S
b11100011101000000101111100000111 ^
b11100011101000000101111100000111 c
1!
#51000
b11 6
#60000
0!
#70000
b10000 3
b10000 A
b10000 G
b10000 j
b10000 1
b10000 D
b10000 Q
b100 R
0b
b100 '
b100 K
b100 \
b100 -
b100 V
b100 r
b11100011101000000100111100000100 /
b11100011101000000100111100000100 S
b11100011101000000100111100000100 ^
b11100011101000000100111100000100 c
b10000 4
b10000 =
b10000 d
b10100 &
b10100 7
b10100 ;
b10100 l
b10000 %
b10000 9
b10000 ?
b10000 B
b11100011101000000010000000000011 "
b11100011101000000010000000000011 ]
b11100011101000000010000000000011 e
b11100011101000000010000000000011 x
b11100011101000000010000000000011 h
1!
#71000
b100 6
#80000
0!
#90000
b11 3
b11 A
b11 G
b11 j
b11 1
b11 D
b11 Q
b0 P
b11 R
1b
b11 '
b11 K
b11 \
b0 )
b0 O
b0 Z
b10 -
b10 V
b10 r
bx "
bx ]
bx e
bx x
bx h
b10100 4
b10100 =
b10100 d
b11000 &
b11000 7
b11000 ;
b11000 l
b10100 %
b10100 9
b10100 ?
b10100 B
b11100011101000000010000000000011 /
b11100011101000000010000000000011 S
b11100011101000000010000000000011 ^
b11100011101000000010000000000011 c
1!
#91000
b101 6
#100000
0!
#110000
xb
bx /
bx S
bx ^
bx c
b11000 4
b11000 =
b11000 d
b11100 &
b11100 7
b11100 ;
b11100 l
b11000 %
b11000 9
b11000 ?
b11000 B
1!
#111000
b110 6
#120000
0!
#130000
b11100 4
b11100 =
b11100 d
b100000 &
b100000 7
b100000 ;
b100000 l
b11100 %
b11100 9
b11100 ?
b11100 B
1!
#131000
b111 6
#140000
0!
#150000
b100000 4
b100000 =
b100000 d
b100100 &
b100100 7
b100100 ;
b100100 l
b100000 %
b100000 9
b100000 ?
b100000 B
1!
#151000
b1000 6
#160000
0!
#170000
b100100 4
b100100 =
b100100 d
b101000 &
b101000 7
b101000 ;
b101000 l
b100100 %
b100100 9
b100100 ?
b100100 B
1!
#171000
b1001 6
#180000
0!
#190000
b101000 4
b101000 =
b101000 d
b101100 &
b101100 7
b101100 ;
b101100 l
b101000 %
b101000 9
b101000 ?
b101000 B
1!
#191000
b1010 6
#200000
0!
#210000
b101100 4
b101100 =
b101100 d
b110000 &
b110000 7
b110000 ;
b110000 l
b101100 %
b101100 9
b101100 ?
b101100 B
1!
#211000
b1011 6
#220000
0!
#230000
b110000 4
b110000 =
b110000 d
b110100 &
b110100 7
b110100 ;
b110100 l
b110000 %
b110000 9
b110000 ?
b110000 B
1!
#231000
b1100 6
#240000
0!
#250000
b110100 4
b110100 =
b110100 d
b111000 &
b111000 7
b111000 ;
b111000 l
b110100 %
b110100 9
b110100 ?
b110100 B
1!
#251000
b1101 6
#260000
0!
#270000
b111000 4
b111000 =
b111000 d
b111100 &
b111100 7
b111100 ;
b111100 l
b111000 %
b111000 9
b111000 ?
b111000 B
1!
#271000
b1110 6
#280000
0!
#290000
b111100 4
b111100 =
b111100 d
b1000000 &
b1000000 7
b1000000 ;
b1000000 l
b111100 %
b111100 9
b111100 ?
b111100 B
1!
#291000
b1111 6
#300000
0!
#310000
b1000000 4
b1000000 =
b1000000 d
b1000100 &
b1000100 7
b1000100 ;
b1000100 l
b1000000 %
b1000000 9
b1000000 ?
b1000000 B
1!
#311000
b10000 6
#320000
0!
#330000
b1000100 4
b1000100 =
b1000100 d
b1001000 &
b1001000 7
b1001000 ;
b1001000 l
b1000100 %
b1000100 9
b1000100 ?
b1000100 B
1!
#331000
b10001 6
#340000
0!
#350000
b1001000 4
b1001000 =
b1001000 d
b1001100 &
b1001100 7
b1001100 ;
b1001100 l
b1001000 %
b1001000 9
b1001000 ?
b1001000 B
1!
#351000
b10010 6
#360000
0!
#370000
b1001100 4
b1001100 =
b1001100 d
b1010000 &
b1010000 7
b1010000 ;
b1010000 l
b1001100 %
b1001100 9
b1001100 ?
b1001100 B
1!
#371000
b10011 6
#380000
0!
#390000
b1010000 4
b1010000 =
b1010000 d
b1010100 &
b1010100 7
b1010100 ;
b1010100 l
b1010000 %
b1010000 9
b1010000 ?
b1010000 B
1!
#391000
b10100 6
#400000
0!
#410000
b1010100 4
b1010100 =
b1010100 d
b1011000 &
b1011000 7
b1011000 ;
b1011000 l
b1010100 %
b1010100 9
b1010100 ?
b1010100 B
1!
#411000
b10101 6
#420000
0!
#430000
b1011000 4
b1011000 =
b1011000 d
b1011100 &
b1011100 7
b1011100 ;
b1011100 l
b1011000 %
b1011000 9
b1011000 ?
b1011000 B
1!
#431000
b10110 6
#440000
0!
#450000
b1011100 4
b1011100 =
b1011100 d
b1100000 &
b1100000 7
b1100000 ;
b1100000 l
b1011100 %
b1011100 9
b1011100 ?
b1011100 B
1!
#451000
b10111 6
#460000
0!
#470000
b1100000 4
b1100000 =
b1100000 d
b1100100 &
b1100100 7
b1100100 ;
b1100100 l
b1100000 %
b1100000 9
b1100000 ?
b1100000 B
1!
#471000
b11000 6
#480000
0!
#490000
b1100100 4
b1100100 =
b1100100 d
b1101000 &
b1101000 7
b1101000 ;
b1101000 l
b1100100 %
b1100100 9
b1100100 ?
b1100100 B
1!
#491000
b11001 6
