section 2/uartmacros.v
`define datasize 8 // bits
`define samplerate 16 // 16 times per 104 us
`define baudrate 9600 // bauds per s
`define timescaleunit 1_000_000_000 // ns
`define clockfrequency 153_600 // baudrate * samplerate

section 2/uart.v
`include "uartmacros.v"

module reciever (
  input clk, 
  input rx
);
  parameter datasize = `datasize;
  parameter samplerate = `samplerate;

  reg [7:0] rreg;
  reg [7:0] cnt;
  reg recieve = 0;

  always @ (posedge clk) begin
    // new byte
    if (rx == 0 & recieve == 0) begin
      recieve <= 1;
      cnt <= 0;
    end
    // store byte
    if (recieve) begin
      if (cnt == samplerate * (datasize + 1)) recieve <= 0;
      else cnt <= cnt + 1;
      // shift register
      if (cnt % samplerate == samplerate / 2) rreg <= rreg << 1 | rx;
    end
  end
endmodule

module transmitter (
  input clk,
  input transmit,
  output tx
);
  parameter datasize = `datasize;
  parameter samplerate = `samplerate;

  reg [7:0] cnt = 0;
  reg [7:0] txreg;
  reg transon;

  reg [7:0] num = 8'haa; // custom number

  assign tx = txreg;

  always @ (posedge clk) begin
    if (transmit) transon <= 1;
    if (transon) begin
      cnt <= cnt + 1;
      if (cnt % samplerate == 0) begin
        case (cnt / samplerate)
          0: txreg <= 0;
          1: txreg <= num[7];
          2: txreg <= num[6];
          3: txreg <= num[5];
          4: txreg <= num[4];
          5: txreg <= num[3];
          6: txreg <= num[2];
          7: txreg <= num[1];
          8: txreg <= num[0];
          9: begin
            txreg <= 1;
            cnt <= 0;
            transon <= 0;
          end
        endcase
      end
    end
  end
endmodule

module uart (
  input transon,
  input clk,
  input rx,
  output tx
);
  reciever recieverModule (.clk(clk), .rx(rx));
  transmitter transmitterModule (.clk(clk), .transmit(transon), .tx(tx));
endmodule

section2/uartTB.v
// iverilog -o uart.out uartTB.v uart.v && ./uart.out
`timescale 1ns/1ps
`include "uartmacros.v"

module uartTB ();
  parameter bitlength = `timescaleunit / `baudrate; // 1/9600 * 10 ** 9 (in ns)


  reg rx1;
  wire tx1;
  reg transon1;
  // clk frequency: 153 600 Hz
  reg clk1 = 0;
  always #((`timescaleunit / `clockfrequency) / 2) clk1 <= ~clk1; // ≈ 3255
  uart uart1 (.clk(clk1), .rx(rx1), .transon(transon1), .tx(tx1));

  //reg rx2;
  //wire tx2;
  //reg transon2;
  //reg clk2 = 0;
  //initial begin
    //#2
    //forever begin
      //#10 clk2 = 1;
      //#10 clk2 = 0;
    //end
  //end
  //uart uart1 (.clk(clk2), .rx(rx2), .transon(transon2), .tx(tx2));

  reg [7:0] num1 = 8'haa;
  reg [7:0] num2 = 8'hf0;
  integer i;

  task recieveNum(input [7:0] val);
    begin
      #bitlength
      rx1 = 0;
      for (i = 7; i >= 0; i = i - 1) begin // from msb to lsb
        #bitlength
        rx1 = val[i];
      end
      #bitlength
      rx1 = 1;
    end
  endtask

  initial begin
    $dumpfile("uart.vcd");
    $dumpvars(0);
    // reciever
    rx1 = 1;
    #100
    recieveNum(num1);
    #100_000
    // transmit
    transon1 = 1;
    #1000
    transon1 = 0;
    #1_000_000 // 1 s extra
    $finish;
  end
endmodule

section 2/uart.vcd
$date
	Tue Jan 10 11:09:38 2023
$end
$version
	Icarus Verilog
$end
$timescale
	1ps
$end
$scope module uartTB $end
$var wire 1 ! tx1 $end
$var reg 1 " clk1 $end
$var reg 8 # num1 [7:0] $end
$var reg 8 $ num2 [7:0] $end
$var reg 1 % rx1 $end
$var reg 1 & transon1 $end
$var integer 32 ' i [31:0] $end
$scope module uart1 $end
$var wire 1 " clk $end
$var wire 1 % rx $end
$var wire 1 & transon $end
$var wire 1 ! tx $end
$scope module recieverModule $end
$var wire 1 " clk $end
$var wire 1 % rx $end
$var reg 8 ( cnt [7:0] $end
$var reg 1 ) recieve $end
$var reg 8 * rreg [7:0] $end
$upscope $end
$scope module transmitterModule $end
$var wire 1 " clk $end
$var wire 1 & transmit $end
$var wire 1 ! tx $end
$var reg 8 + cnt [7:0] $end
$var reg 8 , num [7:0] $end
$var reg 1 - transon $end
$var reg 8 . txreg [7:0] $end
$upscope $end
$upscope $end
$scope task recieveNum $end
$var reg 8 / val [7:0] $end
$upscope $end
$upscope $end
$enddefinitions $end
#0
$dumpvars
bx /
bx .
x-
b10101010 ,
b0 +
bx *
0)
bx (
bx '
x&
1%
b11110000 $
b10101010 #
0"
x!
$end
#100000
b10101010 /
#3255000
1"
#6510000
0"
#9765000
1"
#13020000
0"
#16275000
1"
#19530000
0"
#22785000
1"
#26040000
0"
#29295000
1"
#32550000
0"
#35805000
1"
#39060000
0"
#42315000
1"
#45570000
0"
#48825000
1"
#52080000
0"
#55335000
1"
#58590000
0"
#61845000
1"
#65100000
0"
#68355000
1"
#71610000
0"
#74865000
1"
#78120000
0"
#81375000
1"
#84630000
0"
#87885000
1"
#91140000
0"
#94395000
1"
#97650000
0"
#100905000
1"
#104160000
0"
#104266000
b111 '
0%
#107415000
b0 (
1)
1"
#110670000
0"
#113925000
b1 (
1"
#117180000
0"
#120435000
b10 (
1"
#123690000
0"
#126945000
b11 (
1"
#130200000
0"
#133455000
b100 (
1"
#136710000
0"
#139965000
b101 (
1"
#143220000
0"
#146475000
b110 (
1"
#149730000
0"
#152985000
b111 (
1"
#156240000
0"
#159495000
b1000 (
1"
#162750000
0"
#166005000
bx0 *
b1001 (
1"
#169260000
0"
#172515000
b1010 (
1"
#175770000
0"
#179025000
b1011 (
1"
#182280000
0"
#185535000
b1100 (
1"
#188790000
0"
#192045000
b1101 (
1"
#195300000
0"
#198555000
b1110 (
1"
#201810000
0"
#205065000
b1111 (
1"
#208320000
0"
#208432000
b110 '
1%
#211575000
b10000 (
1"
#214830000
0"
#218085000
b10001 (
1"
#221340000
0"
#224595000
b10010 (
1"
#227850000
0"
#231105000
b10011 (
1"
#234360000
0"
#237615000
b10100 (
1"
#240870000
0"
#244125000
b10101 (
1"
#247380000
0"
#250635000
b10110 (
1"
#253890000
0"
#257145000
b10111 (
1"
#260400000
0"
#263655000
b11000 (
1"
#266910000
0"
#270165000
bx01 *
b11001 (
1"
#273420000
0"
#276675000
b11010 (
1"
#279930000
0"
#283185000
b11011 (
1"
#286440000
0"
#289695000
b11100 (
1"
#292950000
0"
#296205000
b11101 (
1"
#299460000
0"
#302715000
b11110 (
1"
#305970000
0"
#309225000
b11111 (
1"
#312480000
0"
#312598000
b101 '
0%
#315735000
b100000 (
1"
#318990000
0"
#322245000
b100001 (
1"
#325500000
0"
#328755000
b100010 (
1"
#332010000
0"
#335265000
b100011 (
1"
#338520000
0"
#341775000
b100100 (
1"
#345030000
0"
#348285000
b100101 (
1"
#351540000
0"
#354795000
b100110 (
1"
#358050000
0"
#361305000
b100111 (
1"
#364560000
0"
#367815000
b101000 (
1"
#371070000
0"
#374325000
bx010 *
b101001 (
1"
#377580000
0"
#380835000
b101010 (
1"
#384090000
0"
#387345000
b101011 (
1"
#390600000
0"
#393855000
b101100 (
1"
#397110000
0"
#400365000
b101101 (
1"
#403620000
0"
#406875000
b101110 (
1"
#410130000
0"
#413385000
b101111 (
1"
#416640000
0"
#416764000
b100 '
1%
#419895000
b110000 (
1"
#423150000
0"
#426405000
b110001 (
1"
#429660000
0"
#432915000
b110010 (
1"
#436170000
0"
#439425000
b110011 (
1"
#442680000
0"
#445935000
b110100 (
1"
#449190000
0"
#452445000
b110101 (
1"
#455700000
0"
#458955000
b110110 (
1"
#462210000
0"
#465465000
b110111 (
1"
#468720000
0"
#471975000
b111000 (
1"
#475230000
0"
#478485000
bx0101 *
b111001 (
1"
#481740000
0"
#484995000
b111010 (
1"
#488250000
0"
#491505000
b111011 (
1"
#494760000
0"
#498015000
b111100 (
1"
#501270000
0"
#504525000
b111101 (
1"
#507780000
0"
#511035000
b111110 (
1"
#514290000
0"
#517545000
b111111 (
1"
#520800000
0"
#520930000
b11 '
0%
#524055000
b1000000 (
1"
#527310000
0"
#530565000
b1000001 (
1"
#533820000
0"
#537075000
b1000010 (
1"
#540330000
0"
#543585000
b1000011 (
1"
#546840000
0"
#550095000
b1000100 (
1"
#553350000
0"
#556605000
b1000101 (
1"
#559860000
0"
#563115000
b1000110 (
1"
#566370000
0"
#569625000
b1000111 (
1"
#572880000
0"
#576135000
b1001000 (
1"
#579390000
0"
#582645000
bx01010 *
b1001001 (
1"
#585900000
0"
#589155000
b1001010 (
1"
#592410000
0"
#595665000
b1001011 (
1"
#598920000
0"
#602175000
b1001100 (
1"
#605430000
0"
#608685000
b1001101 (
1"
#611940000
0"
#615195000
b1001110 (
1"
#618450000
0"
#621705000
b1001111 (
1"
#624960000
0"
#625096000
b10 '
1%
#628215000
b1010000 (
1"
#631470000
0"
#634725000
b1010001 (
1"
#637980000
0"
#641235000
b1010010 (
1"
#644490000
0"
#647745000
b1010011 (
1"
#651000000
0"
#654255000
b1010100 (
1"
#657510000
0"
#660765000
b1010101 (
1"
#664020000
0"
#667275000
b1010110 (
1"
#670530000
0"
#673785000
b1010111 (
1"
#677040000
0"
#680295000
b1011000 (
1"
#683550000
0"
#686805000
bx010101 *
b1011001 (
1"
#690060000
0"
#693315000
b1011010 (
1"
#696570000
0"
#699825000
b1011011 (
1"
#703080000
0"
#706335000
b1011100 (
1"
#709590000
0"
#712845000
b1011101 (
1"
#716100000
0"
#719355000
b1011110 (
1"
#722610000
0"
#725865000
b1011111 (
1"
#729120000
0"
#729262000
b1 '
0%
#732375000
b1100000 (
1"
#735630000
0"
#738885000
b1100001 (
1"
#742140000
0"
#745395000
b1100010 (
1"
#748650000
0"
#751905000
b1100011 (
1"
#755160000
0"
#758415000
b1100100 (
1"
#761670000
0"
#764925000
b1100101 (
1"
#768180000
0"
#771435000
b1100110 (
1"
#774690000
0"
#777945000
b1100111 (
1"
#781200000
0"
#784455000
b1101000 (
1"
#787710000
0"
#790965000
bx0101010 *
b1101001 (
1"
#794220000
0"
#797475000
b1101010 (
1"
#800730000
0"
#803985000
b1101011 (
1"
#807240000
0"
#810495000
b1101100 (
1"
#813750000
0"
#817005000
b1101101 (
1"
#820260000
0"
#823515000
b1101110 (
1"
#826770000
0"
#830025000
b1101111 (
1"
#833280000
0"
#833428000
b0 '
1%
#836535000
b1110000 (
1"
#839790000
0"
#843045000
b1110001 (
1"
#846300000
0"
#849555000
b1110010 (
1"
#852810000
0"
#856065000
b1110011 (
1"
#859320000
0"
#862575000
b1110100 (
1"
#865830000
0"
#869085000
b1110101 (
1"
#872340000
0"
#875595000
b1110110 (
1"
#878850000
0"
#882105000
b1110111 (
1"
#885360000
0"
#888615000
b1111000 (
1"
#891870000
0"
#895125000
b1010101 *
b1111001 (
1"
#898380000
0"
#901635000
b1111010 (
1"
#904890000
0"
#908145000
b1111011 (
1"
#911400000
0"
#914655000
b1111100 (
1"
#917910000
0"
#921165000
b1111101 (
1"
#924420000
0"
#927675000
b1111110 (
1"
#930930000
0"
#934185000
b1111111 (
1"
#937440000
0"
#937594000
b11111111111111111111111111111111 '
0%
#940695000
b10000000 (
1"
#943950000
0"
#947205000
b10000001 (
1"
#950460000
0"
#953715000
b10000010 (
1"
#956970000
0"
#960225000
b10000011 (
1"
#963480000
0"
#966735000
b10000100 (
1"
#969990000
0"
#973245000
b10000101 (
1"
#976500000
0"
#979755000
b10000110 (
1"
#983010000
0"
#986265000
b10000111 (
1"
#989520000
0"
#992775000
b10001000 (
1"
#996030000
0"
#999285000
b10101010 *
b10001001 (
1"
#1002540000
0"
#1005795000
b10001010 (
1"
#1009050000
0"
#1012305000
b10001011 (
1"
#1015560000
0"
#1018815000
b10001100 (
1"
#1022070000
0"
#1025325000
b10001101 (
1"
#1028580000
0"
#1031835000
b10001110 (
1"
#1035090000
0"
#1038345000
b10001111 (
1"
#1041600000
0"
#1041760000
1%
#1044855000
b10010000 (
1"
#1048110000
0"
#1051365000
0)
1"
#1054620000
0"
#1057875000
1"
#1061130000
0"
#1064385000
1"
#1067640000
0"
#1070895000
1"
#1074150000
0"
#1077405000
1"
#1080660000
0"
#1083915000
1"
#1087170000
0"
#1090425000
1"
#1093680000
0"
#1096935000
1"
#1100190000
0"
#1103445000
1"
#1106700000
0"
#1109955000
1"
#1113210000
0"
#1116465000
1"
#1119720000
0"
#1122975000
1"
#1126230000
0"
#1129485000
1"
#1132740000
0"
#1135995000
1"
#1139250000
0"
#1141760000
1&
#1142505000
1-
1"
#1142760000
0&
#1145760000
0"
#1149015000
0!
b0 .
b1 +
1"
#1152270000
0"
#1155525000
b10 +
1"
#1158780000
0"
#1162035000
b11 +
1"
#1165290000
0"
#1168545000
b100 +
1"
#1171800000
0"
#1175055000
b101 +
1"
#1178310000
0"
#1181565000
b110 +
1"
#1184820000
0"
#1188075000
b111 +
1"
#1191330000
0"
#1194585000
b1000 +
1"
#1197840000
0"
#1201095000
b1001 +
1"
#1204350000
0"
#1207605000
b1010 +
1"
#1210860000
0"
#1214115000
b1011 +
1"
#1217370000
0"
#1220625000
b1100 +
1"
#1223880000
0"
#1227135000
b1101 +
1"
#1230390000
0"
#1233645000
b1110 +
1"
#1236900000
0"
#1240155000
b1111 +
1"
#1243410000
0"
#1246665000
b10000 +
1"
#1249920000
0"
#1253175000
1!
b1 .
b10001 +
1"
#1256430000
0"
#1259685000
b10010 +
1"
#1262940000
0"
#1266195000
b10011 +
1"
#1269450000
0"
#1272705000
b10100 +
1"
#1275960000
0"
#1279215000
b10101 +
1"
#1282470000
0"
#1285725000
b10110 +
1"
#1288980000
0"
#1292235000
b10111 +
1"
#1295490000
0"
#1298745000
b11000 +
1"
#1302000000
0"
#1305255000
b11001 +
1"
#1308510000
0"
#1311765000
b11010 +
1"
#1315020000
0"
#1318275000
b11011 +
1"
#1321530000
0"
#1324785000
b11100 +
1"
#1328040000
0"
#1331295000
b11101 +
1"
#1334550000
0"
#1337805000
b11110 +
1"
#1341060000
0"
#1344315000
b11111 +
1"
#1347570000
0"
#1350825000
b100000 +
1"
#1354080000
0"
#1357335000
0!
b0 .
b100001 +
1"
#1360590000
0"
#1363845000
b100010 +
1"
#1367100000
0"
#1370355000
b100011 +
1"
#1373610000
0"
#1376865000
b100100 +
1"
#1380120000
0"
#1383375000
b100101 +
1"
#1386630000
0"
#1389885000
b100110 +
1"
#1393140000
0"
#1396395000
b100111 +
1"
#1399650000
0"
#1402905000
b101000 +
1"
#1406160000
0"
#1409415000
b101001 +
1"
#1412670000
0"
#1415925000
b101010 +
1"
#1419180000
0"
#1422435000
b101011 +
1"
#1425690000
0"
#1428945000
b101100 +
1"
#1432200000
0"
#1435455000
b101101 +
1"
#1438710000
0"
#1441965000
b101110 +
1"
#1445220000
0"
#1448475000
b101111 +
1"
#1451730000
0"
#1454985000
b110000 +
1"
#1458240000
0"
#1461495000
1!
b1 .
b110001 +
1"
#1464750000
0"
#1468005000
b110010 +
1"
#1471260000
0"
#1474515000
b110011 +
1"
#1477770000
0"
#1481025000
b110100 +
1"
#1484280000
0"
#1487535000
b110101 +
1"
#1490790000
0"
#1494045000
b110110 +
1"
#1497300000
0"
#1500555000
b110111 +
1"
#1503810000
0"
#1507065000
b111000 +
1"
#1510320000
0"
#1513575000
b111001 +
1"
#1516830000
0"
#1520085000
b111010 +
1"
#1523340000
0"
#1526595000
b111011 +
1"
#1529850000
0"
#1533105000
b111100 +
1"
#1536360000
0"
#1539615000
b111101 +
1"
#1542870000
0"
#1546125000
b111110 +
1"
#1549380000
0"
#1552635000
b111111 +
1"
#1555890000
0"
#1559145000
b1000000 +
1"
#1562400000
0"
#1565655000
0!
b0 .
b1000001 +
1"
#1568910000
0"
#1572165000
b1000010 +
1"
#1575420000
0"
#1578675000
b1000011 +
1"
#1581930000
0"
#1585185000
b1000100 +
1"
#1588440000
0"
#1591695000
b1000101 +
1"
#1594950000
0"
#1598205000
b1000110 +
1"
#1601460000
0"
#1604715000
b1000111 +
1"
#1607970000
0"
#1611225000
b1001000 +
1"
#1614480000
0"
#1617735000
b1001001 +
1"
#1620990000
0"
#1624245000
b1001010 +
1"
#1627500000
0"
#1630755000
b1001011 +
1"
#1634010000
0"
#1637265000
b1001100 +
1"
#1640520000
0"
#1643775000
b1001101 +
1"
#1647030000
0"
#1650285000
b1001110 +
1"
#1653540000
0"
#1656795000
b1001111 +
1"
#1660050000
0"
#1663305000
b1010000 +
1"
#1666560000
0"
#1669815000
1!
b1 .
b1010001 +
1"
#1673070000
0"
#1676325000
b1010010 +
1"
#1679580000
0"
#1682835000
b1010011 +
1"
#1686090000
0"
#1689345000
b1010100 +
1"
#1692600000
0"
#1695855000
b1010101 +
1"
#1699110000
0"
#1702365000
b1010110 +
1"
#1705620000
0"
#1708875000
b1010111 +
1"
#1712130000
0"
#1715385000
b1011000 +
1"
#1718640000
0"
#1721895000
b1011001 +
1"
#1725150000
0"
#1728405000
b1011010 +
1"
#1731660000
0"
#1734915000
b1011011 +
1"
#1738170000
0"
#1741425000
b1011100 +
1"
#1744680000
0"
#1747935000
b1011101 +
1"
#1751190000
0"
#1754445000
b1011110 +
1"
#1757700000
0"
#1760955000
b1011111 +
1"
#1764210000
0"
#1767465000
b1100000 +
1"
#1770720000
0"
#1773975000
0!
b0 .
b1100001 +
1"
#1777230000
0"
#1780485000
b1100010 +
1"
#1783740000
0"
#1786995000
b1100011 +
1"
#1790250000
0"
#1793505000
b1100100 +
1"
#1796760000
0"
#1800015000
b1100101 +
1"
#1803270000
0"
#1806525000
b1100110 +
1"
#1809780000
0"
#1813035000
b1100111 +
1"
#1816290000
0"
#1819545000
b1101000 +
1"
#1822800000
0"
#1826055000
b1101001 +
1"
#1829310000
0"
#1832565000
b1101010 +
1"
#1835820000
0"
#1839075000
b1101011 +
1"
#1842330000
0"
#1845585000
b1101100 +
1"
#1848840000
0"
#1852095000
b1101101 +
1"
#1855350000
0"
#1858605000
b1101110 +
1"
#1861860000
0"
#1865115000
b1101111 +
1"
#1868370000
0"
#1871625000
b1110000 +
1"
#1874880000
0"
#1878135000
1!
b1 .
b1110001 +
1"
#1881390000
0"
#1884645000
b1110010 +
1"
#1887900000
0"
#1891155000
b1110011 +
1"
#1894410000
0"
#1897665000
b1110100 +
1"
#1900920000
0"
#1904175000
b1110101 +
1"
#1907430000
0"
#1910685000
b1110110 +
1"
#1913940000
0"
#1917195000
b1110111 +
1"
#1920450000
0"
#1923705000
b1111000 +
1"
#1926960000
0"
#1930215000
b1111001 +
1"
#1933470000
0"
#1936725000
b1111010 +
1"
#1939980000
0"
#1943235000
b1111011 +
1"
#1946490000
0"
#1949745000
b1111100 +
1"
#1953000000
0"
#1956255000
b1111101 +
1"
#1959510000
0"
#1962765000
b1111110 +
1"
#1966020000
0"
#1969275000
b1111111 +
1"
#1972530000
0"
#1975785000
b10000000 +
1"
#1979040000
0"
#1982295000
0!
b0 .
b10000001 +
1"
#1985550000
0"
#1988805000
b10000010 +
1"
#1992060000
0"
#1995315000
b10000011 +
1"
#1998570000
0"
#2001825000
b10000100 +
1"
#2005080000
0"
#2008335000
b10000101 +
1"
#2011590000
0"
#2014845000
b10000110 +
1"
#2018100000
0"
#2021355000
b10000111 +
1"
#2024610000
0"
#2027865000
b10001000 +
1"
#2031120000
0"
#2034375000
b10001001 +
1"
#2037630000
0"
#2040885000
b10001010 +
1"
#2044140000
0"
#2047395000
b10001011 +
1"
#2050650000
0"
#2053905000
b10001100 +
1"
#2057160000
0"
#2060415000
b10001101 +
1"
#2063670000
0"
#2066925000
b10001110 +
1"
#2070180000
0"
#2073435000
b10001111 +
1"
#2076690000
0"
#2079945000
b10010000 +
1"
#2083200000
0"
#2086455000
1!
0-
b1 .
b0 +
1"
